blendconf/__init__.py
blendconf/cli.py
blendconf/py.typed
blendconf-1.0.1.dist-info/WHEEL
blendconf-1.0.1.dist-info/entry_points.txt
blendconf-1.0.1.dist-info/METADATA
blendconf-1.0.1.dist-info/RECORD
