Metadata-Version: 2.3
Name: blendconf
Version: 1.0.1
Summary: Helper to merge multiple configuration files into one file.
Author: Olaf Gladis
Author-email: Olaf Gladis <hwmrocker@gladis.org>
Requires-Dist: python-dotenv>=1.2.1
Requires-Dist: pyyaml>=6.0.3
Requires-Dist: tomli>=2.3.0
Requires-Dist: tomli-w>=1.2.0
Requires-Dist: typer>=0.21.1
Requires-Python: >=3.12
